{
  "metadata" : {
    "identifier" : "https://www.nettruyenio.com/truyen-tranh/no-la-cua-toi-192922",
    "title" : "Nó Là Của Tôi - Chapter 70",
    "subtitle" : null,
    "author" : null,
    "narrator" : null,
    "language" : "vi",
    "description" : null,
    "publisher" : "N/A",
    "subject" : null,
    "modified" : null,
    "published" : "2023-08-07",
    "duration" : 0,
    "abridged" : false,
    "conformsTo" : "https://readium.org/webpub-manifest/profiles/divina",
    "numberOfPages" : 138,
    "readingProgression" : "ttb",
    "belongsTo" : null,
    "presentation" : {
      "fit" : "width",
      "overflow" : "scrolled",
      "continuous" : true
    },
    "@type" : null,
    "schema:license" : null
  },
  "links" : [ {
    "rel" : "self",
    "href" : "https://raw.githubusercontent.com/thuvienonline40/book_storage_collection/main/comic_manifest.json",
    "type" : "application/divina+json"
  } ],
  "readingOrder" : [ {
    "href" : "https://raw.githubusercontent.com/duyhuynh652018/comic_storage8/main/IMAGE/IMAGE_699ba06b8236db9d24f1edeb1e143c06_c979f4919eb191597bcd0feb909c1e54_89551bcf242d4da4cc0dd18916fc65c2.jpg",
    "type" : "image/jpeg",
    "bitrate" : 0,
    "duration" : 0,
    "title" : null,
    "properties" : null,
    "alternate" : [ {
      "href" : "https://i333.ntcdntempv3.com/data/images/19292/907842/001-a82c458.jpg?data=net",
      "type" : "image/jpeg",
      "bitrate" : 0,
      "duration" : 0,
      "title" : null,
      "properties" : null,
      "alternate" : null
    } ]
  }, {
    "href" : "https://raw.githubusercontent.com/duyhuynh652018/comic_storage8/main/IMAGE/IMAGE_699ba06b8236db9d24f1edeb1e143c06_c979f4919eb191597bcd0feb909c1e54_2f14253947ff4e3495ff9a9341f0b66d.jpg",
    "type" : "image/jpeg",
    "bitrate" : 0,
    "duration" : 0,
    "title" : null,
    "properties" : null,
    "alternate" : [ {
      "href" : "https://i333.ntcdntempv3.com/data/images/19292/907842/002-1eac10a.jpg?data=net",
      "type" : "image/jpeg",
      "bitrate" : 0,
      "duration" : 0,
      "title" : null,
      "properties" : null,
      "alternate" : null
    } ]
  }, {
    "href" : "https://raw.githubusercontent.com/duyhuynh652018/comic_storage8/main/IMAGE/IMAGE_699ba06b8236db9d24f1edeb1e143c06_c979f4919eb191597bcd0feb909c1e54_75498a36c6c13b7e6711f815dd42260f.jpg",
    "type" : "image/jpeg",
    "bitrate" : 0,
    "duration" : 0,
    "title" : null,
    "properties" : null,
    "alternate" : [ {
      "href" : "https://i333.ntcdntempv3.com/data/images/19292/907842/003-90b062c.jpg?data=net",
      "type" : "image/jpeg",
      "bitrate" : 0,
      "duration" : 0,
      "title" : null,
      "properties" : null,
      "alternate" : null
    } ]
  }, {
    "href" : "https://raw.githubusercontent.com/duyhuynh652018/comic_storage8/main/IMAGE/IMAGE_699ba06b8236db9d24f1edeb1e143c06_c979f4919eb191597bcd0feb909c1e54_05e3bd55e9a5d91b3e731793a6d534a2.jpg",
    "type" : "image/jpeg",
    "bitrate" : 0,
    "duration" : 0,
    "title" : null,
    "properties" : null,
    "alternate" : [ {
      "href" : "https://i333.ntcdntempv3.com/data/images/19292/907842/004-2deda69.jpg?data=net",
      "type" : "image/jpeg",
      "bitrate" : 0,
      "duration" : 0,
      "title" : null,
      "properties" : null,
      "alternate" : null
    } ]
  }, {
    "href" : "https://raw.githubusercontent.com/duyhuynh652018/comic_storage8/main/IMAGE/IMAGE_699ba06b8236db9d24f1edeb1e143c06_c979f4919eb191597bcd0feb909c1e54_efa1c899b4dc7783a6dd7a464fb64e84.jpg",
    "type" : "image/jpeg",
    "bitrate" : 0,
    "duration" : 0,
    "title" : null,
    "properties" : null,
    "alternate" : [ {
      "href" : "https://i333.ntcdntempv3.com/data/images/19292/907842/005-3ee908b.jpg?data=net",
      "type" : "image/jpeg",
      "bitrate" : 0,
      "duration" : 0,
      "title" : null,
      "properties" : null,
      "alternate" : null
    } ]
  }, {
    "href" : "https://raw.githubusercontent.com/duyhuynh652018/comic_storage8/main/IMAGE/IMAGE_699ba06b8236db9d24f1edeb1e143c06_c979f4919eb191597bcd0feb909c1e54_d92470510094ce1ab26f35bdbca65694.jpg",
    "type" : "image/jpeg",
    "bitrate" : 0,
    "duration" : 0,
    "title" : null,
    "properties" : null,
    "alternate" : [ {
      "href" : "https://i333.ntcdntempv3.com/data/images/19292/907842/006-d56056a.jpg?data=net",
      "type" : "image/jpeg",
      "bitrate" : 0,
      "duration" : 0,
      "title" : null,
      "properties" : null,
      "alternate" : null
    } ]
  }, {
    "href" : "https://raw.githubusercontent.com/duyhuynh652018/comic_storage8/main/IMAGE/IMAGE_699ba06b8236db9d24f1edeb1e143c06_c979f4919eb191597bcd0feb909c1e54_194d2bfaad89262b34d757bebd78d5e1.jpg",
    "type" : "image/jpeg",
    "bitrate" : 0,
    "duration" : 0,
    "title" : null,
    "properties" : null,
    "alternate" : [ {
      "href" : "https://i333.ntcdntempv3.com/data/images/19292/907842/007-c91cb0f.jpg?data=net",
      "type" : "image/jpeg",
      "bitrate" : 0,
      "duration" : 0,
      "title" : null,
      "properties" : null,
      "alternate" : null
    } ]
  }, {
    "href" : "https://raw.githubusercontent.com/duyhuynh652018/comic_storage8/main/IMAGE/IMAGE_699ba06b8236db9d24f1edeb1e143c06_c979f4919eb191597bcd0feb909c1e54_8d799ae9e9e0422375114092b1d471b6.jpg",
    "type" : "image/jpeg",
    "bitrate" : 0,
    "duration" : 0,
    "title" : null,
    "properties" : null,
    "alternate" : [ {
      "href" : "https://i333.ntcdntempv3.com/data/images/19292/907842/008-8e4d044.jpg?data=net",
      "type" : "image/jpeg",
      "bitrate" : 0,
      "duration" : 0,
      "title" : null,
      "properties" : null,
      "alternate" : null
    } ]
  }, {
    "href" : "https://raw.githubusercontent.com/duyhuynh652018/comic_storage8/main/IMAGE/IMAGE_699ba06b8236db9d24f1edeb1e143c06_c979f4919eb191597bcd0feb909c1e54_fb13973870e052f0dccda8a819bbeda6.jpg",
    "type" : "image/jpeg",
    "bitrate" : 0,
    "duration" : 0,
    "title" : null,
    "properties" : null,
    "alternate" : [ {
      "href" : "https://i333.ntcdntempv3.com/data/images/19292/907842/009-81feb24.jpg?data=net",
      "type" : "image/jpeg",
      "bitrate" : 0,
      "duration" : 0,
      "title" : null,
      "properties" : null,
      "alternate" : null
    } ]
  }, {
    "href" : "https://raw.githubusercontent.com/duyhuynh652018/comic_storage8/main/IMAGE/IMAGE_699ba06b8236db9d24f1edeb1e143c06_c979f4919eb191597bcd0feb909c1e54_43d9dacc1b7865dcd61645bac60ca671.jpg",
    "type" : "image/jpeg",
    "bitrate" : 0,
    "duration" : 0,
    "title" : null,
    "properties" : null,
    "alternate" : [ {
      "href" : "https://i333.ntcdntempv3.com/data/images/19292/907842/010-cb901e5.jpg?data=net",
      "type" : "image/jpeg",
      "bitrate" : 0,
      "duration" : 0,
      "title" : null,
      "properties" : null,
      "alternate" : null
    } ]
  }, {
    "href" : "https://raw.githubusercontent.com/duyhuynh652018/comic_storage8/main/IMAGE/IMAGE_699ba06b8236db9d24f1edeb1e143c06_c979f4919eb191597bcd0feb909c1e54_5d035400fcc347df15c991438ffb6ea0.jpg",
    "type" : "image/jpeg",
    "bitrate" : 0,
    "duration" : 0,
    "title" : null,
    "properties" : null,
    "alternate" : [ {
      "href" : "https://i333.ntcdntempv3.com/data/images/19292/907842/011-267ad99.jpg?data=net",
      "type" : "image/jpeg",
      "bitrate" : 0,
      "duration" : 0,
      "title" : null,
      "properties" : null,
      "alternate" : null
    } ]
  }, {
    "href" : "https://raw.githubusercontent.com/duyhuynh652018/comic_storage8/main/IMAGE/IMAGE_699ba06b8236db9d24f1edeb1e143c06_c979f4919eb191597bcd0feb909c1e54_0d19031494a991c1d7fcafdf762dcf06.jpg",
    "type" : "image/jpeg",
    "bitrate" : 0,
    "duration" : 0,
    "title" : null,
    "properties" : null,
    "alternate" : [ {
      "href" : "https://i333.ntcdntempv3.com/data/images/19292/907842/012-b1fce9d.jpg?data=net",
      "type" : "image/jpeg",
      "bitrate" : 0,
      "duration" : 0,
      "title" : null,
      "properties" : null,
      "alternate" : null
    } ]
  }, {
    "href" : "https://raw.githubusercontent.com/duyhuynh652018/comic_storage8/main/IMAGE/IMAGE_699ba06b8236db9d24f1edeb1e143c06_c979f4919eb191597bcd0feb909c1e54_099ae9d790083ce9d90cb0efc42a47f3.jpg",
    "type" : "image/jpeg",
    "bitrate" : 0,
    "duration" : 0,
    "title" : null,
    "properties" : null,
    "alternate" : [ {
      "href" : "https://i333.ntcdntempv3.com/data/images/19292/907842/013-0e1f96f.jpg?data=net",
      "type" : "image/jpeg",
      "bitrate" : 0,
      "duration" : 0,
      "title" : null,
      "properties" : null,
      "alternate" : null
    } ]
  }, {
    "href" : "https://raw.githubusercontent.com/duyhuynh652018/comic_storage8/main/IMAGE/IMAGE_699ba06b8236db9d24f1edeb1e143c06_c979f4919eb191597bcd0feb909c1e54_a0b85afeb3f2af62ca8073a12f570449.jpg",
    "type" : "image/jpeg",
    "bitrate" : 0,
    "duration" : 0,
    "title" : null,
    "properties" : null,
    "alternate" : [ {
      "href" : "https://i333.ntcdntempv3.com/data/images/19292/907842/014-b42da0b.jpg?data=net",
      "type" : "image/jpeg",
      "bitrate" : 0,
      "duration" : 0,
      "title" : null,
      "properties" : null,
      "alternate" : null
    } ]
  }, {
    "href" : "https://raw.githubusercontent.com/duyhuynh652018/comic_storage8/main/IMAGE/IMAGE_699ba06b8236db9d24f1edeb1e143c06_c979f4919eb191597bcd0feb909c1e54_01ac35330e8855501e6f4e1bf5587a27.jpg",
    "type" : "image/jpeg",
    "bitrate" : 0,
    "duration" : 0,
    "title" : null,
    "properties" : null,
    "alternate" : [ {
      "href" : "https://i333.ntcdntempv3.com/data/images/19292/907842/015-fa057c8.jpg?data=net",
      "type" : "image/jpeg",
      "bitrate" : 0,
      "duration" : 0,
      "title" : null,
      "properties" : null,
      "alternate" : null
    } ]
  }, {
    "href" : "https://raw.githubusercontent.com/duyhuynh652018/comic_storage8/main/IMAGE/IMAGE_699ba06b8236db9d24f1edeb1e143c06_c979f4919eb191597bcd0feb909c1e54_f7dd8514b616f4c96d8b2717effc95c6.jpg",
    "type" : "image/jpeg",
    "bitrate" : 0,
    "duration" : 0,
    "title" : null,
    "properties" : null,
    "alternate" : [ {
      "href" : "https://i333.ntcdntempv3.com/data/images/19292/907842/016-09f14c7.jpg?data=net",
      "type" : "image/jpeg",
      "bitrate" : 0,
      "duration" : 0,
      "title" : null,
      "properties" : null,
      "alternate" : null
    } ]
  }, {
    "href" : "https://raw.githubusercontent.com/duyhuynh652018/comic_storage8/main/IMAGE/IMAGE_699ba06b8236db9d24f1edeb1e143c06_c979f4919eb191597bcd0feb909c1e54_cff33b4eb1523b8662a3447802327cb0.jpg",
    "type" : "image/jpeg",
    "bitrate" : 0,
    "duration" : 0,
    "title" : null,
    "properties" : null,
    "alternate" : [ {
      "href" : "https://i333.ntcdntempv3.com/data/images/19292/907842/017-5731994.jpg?data=net",
      "type" : "image/jpeg",
      "bitrate" : 0,
      "duration" : 0,
      "title" : null,
      "properties" : null,
      "alternate" : null
    } ]
  }, {
    "href" : "https://raw.githubusercontent.com/duyhuynh652018/comic_storage8/main/IMAGE/IMAGE_699ba06b8236db9d24f1edeb1e143c06_c979f4919eb191597bcd0feb909c1e54_8c5ed72a9c3c911e57fd20d6acd21e10.jpg",
    "type" : "image/jpeg",
    "bitrate" : 0,
    "duration" : 0,
    "title" : null,
    "properties" : null,
    "alternate" : [ {
      "href" : "https://i333.ntcdntempv3.com/data/images/19292/907842/018-dd0ad60.jpg?data=net",
      "type" : "image/jpeg",
      "bitrate" : 0,
      "duration" : 0,
      "title" : null,
      "properties" : null,
      "alternate" : null
    } ]
  }, {
    "href" : "https://raw.githubusercontent.com/duyhuynh652018/comic_storage8/main/IMAGE/IMAGE_699ba06b8236db9d24f1edeb1e143c06_c979f4919eb191597bcd0feb909c1e54_da1b3c7e71f356015594456768a8d1b0.jpg",
    "type" : "image/jpeg",
    "bitrate" : 0,
    "duration" : 0,
    "title" : null,
    "properties" : null,
    "alternate" : [ {
      "href" : "https://i333.ntcdntempv3.com/data/images/19292/907842/019-9c007a7.jpg?data=net",
      "type" : "image/jpeg",
      "bitrate" : 0,
      "duration" : 0,
      "title" : null,
      "properties" : null,
      "alternate" : null
    } ]
  }, {
    "href" : "https://raw.githubusercontent.com/duyhuynh652018/comic_storage8/main/IMAGE/IMAGE_699ba06b8236db9d24f1edeb1e143c06_c979f4919eb191597bcd0feb909c1e54_92520810fcccd8744b06d7e8295f4436.jpg",
    "type" : "image/jpeg",
    "bitrate" : 0,
    "duration" : 0,
    "title" : null,
    "properties" : null,
    "alternate" : [ {
      "href" : "https://i333.ntcdntempv3.com/data/images/19292/907842/020-4be1b52.jpg?data=net",
      "type" : "image/jpeg",
      "bitrate" : 0,
      "duration" : 0,
      "title" : null,
      "properties" : null,
      "alternate" : null
    } ]
  }, {
    "href" : "https://raw.githubusercontent.com/duyhuynh652018/comic_storage8/main/IMAGE/IMAGE_699ba06b8236db9d24f1edeb1e143c06_c979f4919eb191597bcd0feb909c1e54_7e625323658007b2f0152c2305af4b33.jpg",
    "type" : "image/jpeg",
    "bitrate" : 0,
    "duration" : 0,
    "title" : null,
    "properties" : null,
    "alternate" : [ {
      "href" : "https://i333.ntcdntempv3.com/data/images/19292/907842/021-5396150.jpg?data=net",
      "type" : "image/jpeg",
      "bitrate" : 0,
      "duration" : 0,
      "title" : null,
      "properties" : null,
      "alternate" : null
    } ]
  }, {
    "href" : "https://raw.githubusercontent.com/duyhuynh652018/comic_storage8/main/IMAGE/IMAGE_699ba06b8236db9d24f1edeb1e143c06_c979f4919eb191597bcd0feb909c1e54_0fa94b407becd2b5ff76e2884d209bb8.jpg",
    "type" : "image/jpeg",
    "bitrate" : 0,
    "duration" : 0,
    "title" : null,
    "properties" : null,
    "alternate" : [ {
      "href" : "https://i333.ntcdntempv3.com/data/images/19292/907842/022-49ac73a.jpg?data=net",
      "type" : "image/jpeg",
      "bitrate" : 0,
      "duration" : 0,
      "title" : null,
      "properties" : null,
      "alternate" : null
    } ]
  }, {
    "href" : "https://raw.githubusercontent.com/duyhuynh652018/comic_storage8/main/IMAGE/IMAGE_699ba06b8236db9d24f1edeb1e143c06_c979f4919eb191597bcd0feb909c1e54_d3dae91e12959d77353dab415f0022db.jpg",
    "type" : "image/jpeg",
    "bitrate" : 0,
    "duration" : 0,
    "title" : null,
    "properties" : null,
    "alternate" : [ {
      "href" : "https://i333.ntcdntempv3.com/data/images/19292/907842/023-b9b050f.jpg?data=net",
      "type" : "image/jpeg",
      "bitrate" : 0,
      "duration" : 0,
      "title" : null,
      "properties" : null,
      "alternate" : null
    } ]
  }, {
    "href" : "https://raw.githubusercontent.com/duyhuynh652018/comic_storage8/main/IMAGE/IMAGE_699ba06b8236db9d24f1edeb1e143c06_c979f4919eb191597bcd0feb909c1e54_e61c978e425a8b559fc3d8633ea74353.jpg",
    "type" : "image/jpeg",
    "bitrate" : 0,
    "duration" : 0,
    "title" : null,
    "properties" : null,
    "alternate" : [ {
      "href" : "https://i333.ntcdntempv3.com/data/images/19292/907842/024-7599434.jpg?data=net",
      "type" : "image/jpeg",
      "bitrate" : 0,
      "duration" : 0,
      "title" : null,
      "properties" : null,
      "alternate" : null
    } ]
  }, {
    "href" : "https://raw.githubusercontent.com/duyhuynh652018/comic_storage8/main/IMAGE/IMAGE_699ba06b8236db9d24f1edeb1e143c06_c979f4919eb191597bcd0feb909c1e54_cf0ecf5110feb829160da6659a9a585d.jpg",
    "type" : "image/jpeg",
    "bitrate" : 0,
    "duration" : 0,
    "title" : null,
    "properties" : null,
    "alternate" : [ {
      "href" : "https://i333.ntcdntempv3.com/data/images/19292/907842/025-cea84da.jpg?data=net",
      "type" : "image/jpeg",
      "bitrate" : 0,
      "duration" : 0,
      "title" : null,
      "properties" : null,
      "alternate" : null
    } ]
  }, {
    "href" : "https://raw.githubusercontent.com/duyhuynh652018/comic_storage8/main/IMAGE/IMAGE_699ba06b8236db9d24f1edeb1e143c06_c979f4919eb191597bcd0feb909c1e54_12b31f537422aa6213a3caf7f97b2f49.jpg",
    "type" : "image/jpeg",
    "bitrate" : 0,
    "duration" : 0,
    "title" : null,
    "properties" : null,
    "alternate" : [ {
      "href" : "https://i333.ntcdntempv3.com/data/images/19292/907842/026-2b73783.jpg?data=net",
      "type" : "image/jpeg",
      "bitrate" : 0,
      "duration" : 0,
      "title" : null,
      "properties" : null,
      "alternate" : null
    } ]
  }, {
    "href" : "https://raw.githubusercontent.com/duyhuynh652018/comic_storage8/main/IMAGE/IMAGE_699ba06b8236db9d24f1edeb1e143c06_c979f4919eb191597bcd0feb909c1e54_d8cca5f110c12fd387d5576cca3ab9b4.jpg",
    "type" : "image/jpeg",
    "bitrate" : 0,
    "duration" : 0,
    "title" : null,
    "properties" : null,
    "alternate" : [ {
      "href" : "https://i333.ntcdntempv3.com/data/images/19292/907842/027-1978c07.jpg?data=net",
      "type" : "image/jpeg",
      "bitrate" : 0,
      "duration" : 0,
      "title" : null,
      "properties" : null,
      "alternate" : null
    } ]
  }, {
    "href" : "https://raw.githubusercontent.com/duyhuynh652018/comic_storage8/main/IMAGE/IMAGE_699ba06b8236db9d24f1edeb1e143c06_c979f4919eb191597bcd0feb909c1e54_60656d484ddee86b04fbff7b23a9dbe8.jpg",
    "type" : "image/jpeg",
    "bitrate" : 0,
    "duration" : 0,
    "title" : null,
    "properties" : null,
    "alternate" : [ {
      "href" : "https://i333.ntcdntempv3.com/data/images/19292/907842/028-72887df.jpg?data=net",
      "type" : "image/jpeg",
      "bitrate" : 0,
      "duration" : 0,
      "title" : null,
      "properties" : null,
      "alternate" : null
    } ]
  }, {
    "href" : "https://raw.githubusercontent.com/duyhuynh652018/comic_storage8/main/IMAGE/IMAGE_699ba06b8236db9d24f1edeb1e143c06_c979f4919eb191597bcd0feb909c1e54_70c3569a4a4904fa8b26070a1d817caf.jpg",
    "type" : "image/jpeg",
    "bitrate" : 0,
    "duration" : 0,
    "title" : null,
    "properties" : null,
    "alternate" : [ {
      "href" : "https://i333.ntcdntempv3.com/data/images/19292/907842/029-2d1ffd0.jpg?data=net",
      "type" : "image/jpeg",
      "bitrate" : 0,
      "duration" : 0,
      "title" : null,
      "properties" : null,
      "alternate" : null
    } ]
  }, {
    "href" : "https://raw.githubusercontent.com/duyhuynh652018/comic_storage8/main/IMAGE/IMAGE_699ba06b8236db9d24f1edeb1e143c06_c979f4919eb191597bcd0feb909c1e54_61b674f0a546d6e1cb716442ef2de318.jpg",
    "type" : "image/jpeg",
    "bitrate" : 0,
    "duration" : 0,
    "title" : null,
    "properties" : null,
    "alternate" : [ {
      "href" : "https://i333.ntcdntempv3.com/data/images/19292/907842/030-e3a94ef.jpg?data=net",
      "type" : "image/jpeg",
      "bitrate" : 0,
      "duration" : 0,
      "title" : null,
      "properties" : null,
      "alternate" : null
    } ]
  }, {
    "href" : "https://raw.githubusercontent.com/duyhuynh652018/comic_storage8/main/IMAGE/IMAGE_699ba06b8236db9d24f1edeb1e143c06_c979f4919eb191597bcd0feb909c1e54_70567b7275d403137aaa9505b31a8070.jpg",
    "type" : "image/jpeg",
    "bitrate" : 0,
    "duration" : 0,
    "title" : null,
    "properties" : null,
    "alternate" : [ {
      "href" : "https://i333.ntcdntempv3.com/data/images/19292/907842/031-f6193c0.jpg?data=net",
      "type" : "image/jpeg",
      "bitrate" : 0,
      "duration" : 0,
      "title" : null,
      "properties" : null,
      "alternate" : null
    } ]
  }, {
    "href" : "https://raw.githubusercontent.com/duyhuynh652018/comic_storage8/main/IMAGE/IMAGE_699ba06b8236db9d24f1edeb1e143c06_c979f4919eb191597bcd0feb909c1e54_65bf72a7b68c2fc65e594c89e61e3a75.jpg",
    "type" : "image/jpeg",
    "bitrate" : 0,
    "duration" : 0,
    "title" : null,
    "properties" : null,
    "alternate" : [ {
      "href" : "https://i333.ntcdntempv3.com/data/images/19292/907842/032-bdefa7e.jpg?data=net",
      "type" : "image/jpeg",
      "bitrate" : 0,
      "duration" : 0,
      "title" : null,
      "properties" : null,
      "alternate" : null
    } ]
  }, {
    "href" : "https://raw.githubusercontent.com/duyhuynh652018/comic_storage8/main/IMAGE/IMAGE_699ba06b8236db9d24f1edeb1e143c06_c979f4919eb191597bcd0feb909c1e54_389355256eab3c2c5ae4d3e5ae0ca048.jpg",
    "type" : "image/jpeg",
    "bitrate" : 0,
    "duration" : 0,
    "title" : null,
    "properties" : null,
    "alternate" : [ {
      "href" : "https://i333.ntcdntempv3.com/data/images/19292/907842/033-5bd234e.jpg?data=net",
      "type" : "image/jpeg",
      "bitrate" : 0,
      "duration" : 0,
      "title" : null,
      "properties" : null,
      "alternate" : null
    } ]
  }, {
    "href" : "https://raw.githubusercontent.com/duyhuynh652018/comic_storage8/main/IMAGE/IMAGE_699ba06b8236db9d24f1edeb1e143c06_c979f4919eb191597bcd0feb909c1e54_130e5f76b2dfa40c38f92308c2e51816.jpg",
    "type" : "image/jpeg",
    "bitrate" : 0,
    "duration" : 0,
    "title" : null,
    "properties" : null,
    "alternate" : [ {
      "href" : "https://i333.ntcdntempv3.com/data/images/19292/907842/034-ddb9449.jpg?data=net",
      "type" : "image/jpeg",
      "bitrate" : 0,
      "duration" : 0,
      "title" : null,
      "properties" : null,
      "alternate" : null
    } ]
  }, {
    "href" : "https://raw.githubusercontent.com/duyhuynh652018/comic_storage8/main/IMAGE/IMAGE_699ba06b8236db9d24f1edeb1e143c06_c979f4919eb191597bcd0feb909c1e54_58cea441851c83eccb6829ccb19c4043.jpg",
    "type" : "image/jpeg",
    "bitrate" : 0,
    "duration" : 0,
    "title" : null,
    "properties" : null,
    "alternate" : [ {
      "href" : "https://i333.ntcdntempv3.com/data/images/19292/907842/035-7e9d655.jpg?data=net",
      "type" : "image/jpeg",
      "bitrate" : 0,
      "duration" : 0,
      "title" : null,
      "properties" : null,
      "alternate" : null
    } ]
  }, {
    "href" : "https://raw.githubusercontent.com/duyhuynh652018/comic_storage8/main/IMAGE/IMAGE_699ba06b8236db9d24f1edeb1e143c06_c979f4919eb191597bcd0feb909c1e54_1eb0930bc01d541a74cde01a1348862c.jpg",
    "type" : "image/jpeg",
    "bitrate" : 0,
    "duration" : 0,
    "title" : null,
    "properties" : null,
    "alternate" : [ {
      "href" : "https://i333.ntcdntempv3.com/data/images/19292/907842/036-dc559e8.jpg?data=net",
      "type" : "image/jpeg",
      "bitrate" : 0,
      "duration" : 0,
      "title" : null,
      "properties" : null,
      "alternate" : null
    } ]
  }, {
    "href" : "https://raw.githubusercontent.com/duyhuynh652018/comic_storage8/main/IMAGE/IMAGE_699ba06b8236db9d24f1edeb1e143c06_c979f4919eb191597bcd0feb909c1e54_5f1bdd884f5facda47f09aaa5de18821.jpg",
    "type" : "image/jpeg",
    "bitrate" : 0,
    "duration" : 0,
    "title" : null,
    "properties" : null,
    "alternate" : [ {
      "href" : "https://i333.ntcdntempv3.com/data/images/19292/907842/037-403981e.jpg?data=net",
      "type" : "image/jpeg",
      "bitrate" : 0,
      "duration" : 0,
      "title" : null,
      "properties" : null,
      "alternate" : null
    } ]
  }, {
    "href" : "https://raw.githubusercontent.com/duyhuynh652018/comic_storage8/main/IMAGE/IMAGE_699ba06b8236db9d24f1edeb1e143c06_c979f4919eb191597bcd0feb909c1e54_306c0603b2b50057d4b2d209fa79f88d.jpg",
    "type" : "image/jpeg",
    "bitrate" : 0,
    "duration" : 0,
    "title" : null,
    "properties" : null,
    "alternate" : [ {
      "href" : "https://i333.ntcdntempv3.com/data/images/19292/907842/038-280dd5a.jpg?data=net",
      "type" : "image/jpeg",
      "bitrate" : 0,
      "duration" : 0,
      "title" : null,
      "properties" : null,
      "alternate" : null
    } ]
  }, {
    "href" : "https://raw.githubusercontent.com/duyhuynh652018/comic_storage8/main/IMAGE/IMAGE_699ba06b8236db9d24f1edeb1e143c06_c979f4919eb191597bcd0feb909c1e54_4b969fc454be5f0552d7cda4121af3ba.jpg",
    "type" : "image/jpeg",
    "bitrate" : 0,
    "duration" : 0,
    "title" : null,
    "properties" : null,
    "alternate" : [ {
      "href" : "https://i333.ntcdntempv3.com/data/images/19292/907842/039-72e0f97.jpg?data=net",
      "type" : "image/jpeg",
      "bitrate" : 0,
      "duration" : 0,
      "title" : null,
      "properties" : null,
      "alternate" : null
    } ]
  }, {
    "href" : "https://raw.githubusercontent.com/duyhuynh652018/comic_storage8/main/IMAGE/IMAGE_699ba06b8236db9d24f1edeb1e143c06_c979f4919eb191597bcd0feb909c1e54_50b6685acdfebdc38ff1eab2510fbb49.jpg",
    "type" : "image/jpeg",
    "bitrate" : 0,
    "duration" : 0,
    "title" : null,
    "properties" : null,
    "alternate" : [ {
      "href" : "https://i333.ntcdntempv3.com/data/images/19292/907842/040-aa894f7.jpg?data=net",
      "type" : "image/jpeg",
      "bitrate" : 0,
      "duration" : 0,
      "title" : null,
      "properties" : null,
      "alternate" : null
    } ]
  }, {
    "href" : "https://raw.githubusercontent.com/duyhuynh652018/comic_storage8/main/IMAGE/IMAGE_699ba06b8236db9d24f1edeb1e143c06_c979f4919eb191597bcd0feb909c1e54_beda64bb37c859dc3226f43e4f92b29a.jpg",
    "type" : "image/jpeg",
    "bitrate" : 0,
    "duration" : 0,
    "title" : null,
    "properties" : null,
    "alternate" : [ {
      "href" : "https://i333.ntcdntempv3.com/data/images/19292/907842/041-9958cda.jpg?data=net",
      "type" : "image/jpeg",
      "bitrate" : 0,
      "duration" : 0,
      "title" : null,
      "properties" : null,
      "alternate" : null
    } ]
  }, {
    "href" : "https://raw.githubusercontent.com/duyhuynh652018/comic_storage8/main/IMAGE/IMAGE_699ba06b8236db9d24f1edeb1e143c06_c979f4919eb191597bcd0feb909c1e54_2f068c52513a84e8d8bf1d1ecbddddd6.jpg",
    "type" : "image/jpeg",
    "bitrate" : 0,
    "duration" : 0,
    "title" : null,
    "properties" : null,
    "alternate" : [ {
      "href" : "https://i333.ntcdntempv3.com/data/images/19292/907842/042-9b2fa84.jpg?data=net",
      "type" : "image/jpeg",
      "bitrate" : 0,
      "duration" : 0,
      "title" : null,
      "properties" : null,
      "alternate" : null
    } ]
  }, {
    "href" : "https://raw.githubusercontent.com/duyhuynh652018/comic_storage8/main/IMAGE/IMAGE_699ba06b8236db9d24f1edeb1e143c06_c979f4919eb191597bcd0feb909c1e54_b500ec8321d0ee65da9840bd98cb856c.jpg",
    "type" : "image/jpeg",
    "bitrate" : 0,
    "duration" : 0,
    "title" : null,
    "properties" : null,
    "alternate" : [ {
      "href" : "https://i333.ntcdntempv3.com/data/images/19292/907842/043-0677059.jpg?data=net",
      "type" : "image/jpeg",
      "bitrate" : 0,
      "duration" : 0,
      "title" : null,
      "properties" : null,
      "alternate" : null
    } ]
  }, {
    "href" : "https://raw.githubusercontent.com/duyhuynh652018/comic_storage8/main/IMAGE/IMAGE_699ba06b8236db9d24f1edeb1e143c06_c979f4919eb191597bcd0feb909c1e54_fd9420f13d9dd91526bb40ec8fc4ae38.jpg",
    "type" : "image/jpeg",
    "bitrate" : 0,
    "duration" : 0,
    "title" : null,
    "properties" : null,
    "alternate" : [ {
      "href" : "https://i333.ntcdntempv3.com/data/images/19292/907842/044-1d47cd9.jpg?data=net",
      "type" : "image/jpeg",
      "bitrate" : 0,
      "duration" : 0,
      "title" : null,
      "properties" : null,
      "alternate" : null
    } ]
  }, {
    "href" : "https://raw.githubusercontent.com/duyhuynh652018/comic_storage8/main/IMAGE/IMAGE_699ba06b8236db9d24f1edeb1e143c06_c979f4919eb191597bcd0feb909c1e54_0870552aa42237a48e4b23afe30b8ef1.jpg",
    "type" : "image/jpeg",
    "bitrate" : 0,
    "duration" : 0,
    "title" : null,
    "properties" : null,
    "alternate" : [ {
      "href" : "https://i333.ntcdntempv3.com/data/images/19292/907842/045-6b4564e.jpg?data=net",
      "type" : "image/jpeg",
      "bitrate" : 0,
      "duration" : 0,
      "title" : null,
      "properties" : null,
      "alternate" : null
    } ]
  }, {
    "href" : "https://raw.githubusercontent.com/duyhuynh652018/comic_storage8/main/IMAGE/IMAGE_699ba06b8236db9d24f1edeb1e143c06_c979f4919eb191597bcd0feb909c1e54_d36be8b1b354439e4e18bdef70fc8b4b.jpg",
    "type" : "image/jpeg",
    "bitrate" : 0,
    "duration" : 0,
    "title" : null,
    "properties" : null,
    "alternate" : [ {
      "href" : "https://i333.ntcdntempv3.com/data/images/19292/907842/046-c634c2f.jpg?data=net",
      "type" : "image/jpeg",
      "bitrate" : 0,
      "duration" : 0,
      "title" : null,
      "properties" : null,
      "alternate" : null
    } ]
  }, {
    "href" : "https://raw.githubusercontent.com/duyhuynh652018/comic_storage8/main/IMAGE/IMAGE_699ba06b8236db9d24f1edeb1e143c06_c979f4919eb191597bcd0feb909c1e54_ff2ba31dec528b7e5ec2f228831b52d5.jpg",
    "type" : "image/jpeg",
    "bitrate" : 0,
    "duration" : 0,
    "title" : null,
    "properties" : null,
    "alternate" : [ {
      "href" : "https://i333.ntcdntempv3.com/data/images/19292/907842/047-c31f772.jpg?data=net",
      "type" : "image/jpeg",
      "bitrate" : 0,
      "duration" : 0,
      "title" : null,
      "properties" : null,
      "alternate" : null
    } ]
  }, {
    "href" : "https://raw.githubusercontent.com/duyhuynh652018/comic_storage8/main/IMAGE/IMAGE_699ba06b8236db9d24f1edeb1e143c06_c979f4919eb191597bcd0feb909c1e54_c6a76a64698aff0f85222877122cdf06.jpg",
    "type" : "image/jpeg",
    "bitrate" : 0,
    "duration" : 0,
    "title" : null,
    "properties" : null,
    "alternate" : [ {
      "href" : "https://i333.ntcdntempv3.com/data/images/19292/907842/048-ec238ac.jpg?data=net",
      "type" : "image/jpeg",
      "bitrate" : 0,
      "duration" : 0,
      "title" : null,
      "properties" : null,
      "alternate" : null
    } ]
  }, {
    "href" : "https://raw.githubusercontent.com/duyhuynh652018/comic_storage8/main/IMAGE/IMAGE_699ba06b8236db9d24f1edeb1e143c06_c979f4919eb191597bcd0feb909c1e54_498515cec26cc86e634afdb18c0b463f.jpg",
    "type" : "image/jpeg",
    "bitrate" : 0,
    "duration" : 0,
    "title" : null,
    "properties" : null,
    "alternate" : [ {
      "href" : "https://i333.ntcdntempv3.com/data/images/19292/907842/049-77b6934.jpg?data=net",
      "type" : "image/jpeg",
      "bitrate" : 0,
      "duration" : 0,
      "title" : null,
      "properties" : null,
      "alternate" : null
    } ]
  }, {
    "href" : "https://raw.githubusercontent.com/duyhuynh652018/comic_storage8/main/IMAGE/IMAGE_699ba06b8236db9d24f1edeb1e143c06_c979f4919eb191597bcd0feb909c1e54_a72d2f914c864c6ae78c4f55648eeea0.jpg",
    "type" : "image/jpeg",
    "bitrate" : 0,
    "duration" : 0,
    "title" : null,
    "properties" : null,
    "alternate" : [ {
      "href" : "https://i333.ntcdntempv3.com/data/images/19292/907842/050-46bfcfb.jpg?data=net",
      "type" : "image/jpeg",
      "bitrate" : 0,
      "duration" : 0,
      "title" : null,
      "properties" : null,
      "alternate" : null
    } ]
  }, {
    "href" : "https://raw.githubusercontent.com/duyhuynh652018/comic_storage8/main/IMAGE/IMAGE_699ba06b8236db9d24f1edeb1e143c06_c979f4919eb191597bcd0feb909c1e54_dfca2cb12c5496e9d71e8a6c68a4e674.jpg",
    "type" : "image/jpeg",
    "bitrate" : 0,
    "duration" : 0,
    "title" : null,
    "properties" : null,
    "alternate" : [ {
      "href" : "https://i333.ntcdntempv3.com/data/images/19292/907842/051-41de7df.jpg?data=net",
      "type" : "image/jpeg",
      "bitrate" : 0,
      "duration" : 0,
      "title" : null,
      "properties" : null,
      "alternate" : null
    } ]
  }, {
    "href" : "https://raw.githubusercontent.com/duyhuynh652018/comic_storage8/main/IMAGE/IMAGE_699ba06b8236db9d24f1edeb1e143c06_c979f4919eb191597bcd0feb909c1e54_ed495f48557a4f83b11be13550f6bff9.jpg",
    "type" : "image/jpeg",
    "bitrate" : 0,
    "duration" : 0,
    "title" : null,
    "properties" : null,
    "alternate" : [ {
      "href" : "https://i333.ntcdntempv3.com/data/images/19292/907842/052-f00045e.jpg?data=net",
      "type" : "image/jpeg",
      "bitrate" : 0,
      "duration" : 0,
      "title" : null,
      "properties" : null,
      "alternate" : null
    } ]
  }, {
    "href" : "https://raw.githubusercontent.com/duyhuynh652018/comic_storage8/main/IMAGE/IMAGE_699ba06b8236db9d24f1edeb1e143c06_c979f4919eb191597bcd0feb909c1e54_1e8e09cfce4e6eea7feaa0aec0de99a7.jpg",
    "type" : "image/jpeg",
    "bitrate" : 0,
    "duration" : 0,
    "title" : null,
    "properties" : null,
    "alternate" : [ {
      "href" : "https://i333.ntcdntempv3.com/data/images/19292/907842/053-7956101.jpg?data=net",
      "type" : "image/jpeg",
      "bitrate" : 0,
      "duration" : 0,
      "title" : null,
      "properties" : null,
      "alternate" : null
    } ]
  }, {
    "href" : "https://raw.githubusercontent.com/duyhuynh652018/comic_storage8/main/IMAGE/IMAGE_699ba06b8236db9d24f1edeb1e143c06_c979f4919eb191597bcd0feb909c1e54_5186f2424ec4c1dff215da0496fb58b8.jpg",
    "type" : "image/jpeg",
    "bitrate" : 0,
    "duration" : 0,
    "title" : null,
    "properties" : null,
    "alternate" : [ {
      "href" : "https://i333.ntcdntempv3.com/data/images/19292/907842/054-17b1400.jpg?data=net",
      "type" : "image/jpeg",
      "bitrate" : 0,
      "duration" : 0,
      "title" : null,
      "properties" : null,
      "alternate" : null
    } ]
  }, {
    "href" : "https://raw.githubusercontent.com/duyhuynh652018/comic_storage8/main/IMAGE/IMAGE_699ba06b8236db9d24f1edeb1e143c06_c979f4919eb191597bcd0feb909c1e54_8ba918f92f0f8cbd29654e390e5870f9.jpg",
    "type" : "image/jpeg",
    "bitrate" : 0,
    "duration" : 0,
    "title" : null,
    "properties" : null,
    "alternate" : [ {
      "href" : "https://i333.ntcdntempv3.com/data/images/19292/907842/055-900a623.jpg?data=net",
      "type" : "image/jpeg",
      "bitrate" : 0,
      "duration" : 0,
      "title" : null,
      "properties" : null,
      "alternate" : null
    } ]
  }, {
    "href" : "https://raw.githubusercontent.com/duyhuynh652018/comic_storage8/main/IMAGE/IMAGE_699ba06b8236db9d24f1edeb1e143c06_c979f4919eb191597bcd0feb909c1e54_67442bf5b964ff795631737745848639.jpg",
    "type" : "image/jpeg",
    "bitrate" : 0,
    "duration" : 0,
    "title" : null,
    "properties" : null,
    "alternate" : [ {
      "href" : "https://i333.ntcdntempv3.com/data/images/19292/907842/056-975a479.jpg?data=net",
      "type" : "image/jpeg",
      "bitrate" : 0,
      "duration" : 0,
      "title" : null,
      "properties" : null,
      "alternate" : null
    } ]
  }, {
    "href" : "https://raw.githubusercontent.com/duyhuynh652018/comic_storage8/main/IMAGE/IMAGE_699ba06b8236db9d24f1edeb1e143c06_c979f4919eb191597bcd0feb909c1e54_88c7c8e45a20ccf3c01ab3951181b90c.jpg",
    "type" : "image/jpeg",
    "bitrate" : 0,
    "duration" : 0,
    "title" : null,
    "properties" : null,
    "alternate" : [ {
      "href" : "https://i333.ntcdntempv3.com/data/images/19292/907842/057-df9575e.jpg?data=net",
      "type" : "image/jpeg",
      "bitrate" : 0,
      "duration" : 0,
      "title" : null,
      "properties" : null,
      "alternate" : null
    } ]
  }, {
    "href" : "https://raw.githubusercontent.com/duyhuynh652018/comic_storage8/main/IMAGE/IMAGE_699ba06b8236db9d24f1edeb1e143c06_c979f4919eb191597bcd0feb909c1e54_44137931f5b36089d19710ce6b64dc1a.jpg",
    "type" : "image/jpeg",
    "bitrate" : 0,
    "duration" : 0,
    "title" : null,
    "properties" : null,
    "alternate" : [ {
      "href" : "https://i333.ntcdntempv3.com/data/images/19292/907842/058-abbfd2a.jpg?data=net",
      "type" : "image/jpeg",
      "bitrate" : 0,
      "duration" : 0,
      "title" : null,
      "properties" : null,
      "alternate" : null
    } ]
  }, {
    "href" : "https://raw.githubusercontent.com/duyhuynh652018/comic_storage8/main/IMAGE/IMAGE_699ba06b8236db9d24f1edeb1e143c06_c979f4919eb191597bcd0feb909c1e54_e50827174b463f931411801e0915ced8.jpg",
    "type" : "image/jpeg",
    "bitrate" : 0,
    "duration" : 0,
    "title" : null,
    "properties" : null,
    "alternate" : [ {
      "href" : "https://i333.ntcdntempv3.com/data/images/19292/907842/059-69a03fe.jpg?data=net",
      "type" : "image/jpeg",
      "bitrate" : 0,
      "duration" : 0,
      "title" : null,
      "properties" : null,
      "alternate" : null
    } ]
  }, {
    "href" : "https://raw.githubusercontent.com/duyhuynh652018/comic_storage8/main/IMAGE/IMAGE_699ba06b8236db9d24f1edeb1e143c06_c979f4919eb191597bcd0feb909c1e54_bfa4fc23711db22920bd6d618c3ddaa4.jpg",
    "type" : "image/jpeg",
    "bitrate" : 0,
    "duration" : 0,
    "title" : null,
    "properties" : null,
    "alternate" : [ {
      "href" : "https://i333.ntcdntempv3.com/data/images/19292/907842/060-3495051.jpg?data=net",
      "type" : "image/jpeg",
      "bitrate" : 0,
      "duration" : 0,
      "title" : null,
      "properties" : null,
      "alternate" : null
    } ]
  }, {
    "href" : "https://raw.githubusercontent.com/duyhuynh652018/comic_storage8/main/IMAGE/IMAGE_699ba06b8236db9d24f1edeb1e143c06_c979f4919eb191597bcd0feb909c1e54_a1f63c947caa43149fa04802cb83700d.jpg",
    "type" : "image/jpeg",
    "bitrate" : 0,
    "duration" : 0,
    "title" : null,
    "properties" : null,
    "alternate" : [ {
      "href" : "https://i333.ntcdntempv3.com/data/images/19292/907842/061-4a16c0c.jpg?data=net",
      "type" : "image/jpeg",
      "bitrate" : 0,
      "duration" : 0,
      "title" : null,
      "properties" : null,
      "alternate" : null
    } ]
  }, {
    "href" : "https://raw.githubusercontent.com/duyhuynh652018/comic_storage8/main/IMAGE/IMAGE_699ba06b8236db9d24f1edeb1e143c06_c979f4919eb191597bcd0feb909c1e54_e5ad87a53444c95849ddcfce29f7f528.jpg",
    "type" : "image/jpeg",
    "bitrate" : 0,
    "duration" : 0,
    "title" : null,
    "properties" : null,
    "alternate" : [ {
      "href" : "https://i333.ntcdntempv3.com/data/images/19292/907842/062-669e3b0.jpg?data=net",
      "type" : "image/jpeg",
      "bitrate" : 0,
      "duration" : 0,
      "title" : null,
      "properties" : null,
      "alternate" : null
    } ]
  }, {
    "href" : "https://raw.githubusercontent.com/duyhuynh652018/comic_storage8/main/IMAGE/IMAGE_699ba06b8236db9d24f1edeb1e143c06_c979f4919eb191597bcd0feb909c1e54_5435629df4248cc546ea06a6eaeae729.jpg",
    "type" : "image/jpeg",
    "bitrate" : 0,
    "duration" : 0,
    "title" : null,
    "properties" : null,
    "alternate" : [ {
      "href" : "https://i333.ntcdntempv3.com/data/images/19292/907842/063-07ca494.jpg?data=net",
      "type" : "image/jpeg",
      "bitrate" : 0,
      "duration" : 0,
      "title" : null,
      "properties" : null,
      "alternate" : null
    } ]
  }, {
    "href" : "https://raw.githubusercontent.com/duyhuynh652018/comic_storage8/main/IMAGE/IMAGE_699ba06b8236db9d24f1edeb1e143c06_c979f4919eb191597bcd0feb909c1e54_98ed82c914f0437e8fd92ce81c2233b9.jpg",
    "type" : "image/jpeg",
    "bitrate" : 0,
    "duration" : 0,
    "title" : null,
    "properties" : null,
    "alternate" : [ {
      "href" : "https://i333.ntcdntempv3.com/data/images/19292/907842/064-b3249be.jpg?data=net",
      "type" : "image/jpeg",
      "bitrate" : 0,
      "duration" : 0,
      "title" : null,
      "properties" : null,
      "alternate" : null
    } ]
  }, {
    "href" : "https://raw.githubusercontent.com/duyhuynh652018/comic_storage8/main/IMAGE/IMAGE_699ba06b8236db9d24f1edeb1e143c06_c979f4919eb191597bcd0feb909c1e54_d4625c81f445f57fc6843258a8b1f0e2.jpg",
    "type" : "image/jpeg",
    "bitrate" : 0,
    "duration" : 0,
    "title" : null,
    "properties" : null,
    "alternate" : [ {
      "href" : "https://i333.ntcdntempv3.com/data/images/19292/907842/065-3cb4723.jpg?data=net",
      "type" : "image/jpeg",
      "bitrate" : 0,
      "duration" : 0,
      "title" : null,
      "properties" : null,
      "alternate" : null
    } ]
  }, {
    "href" : "https://raw.githubusercontent.com/duyhuynh652018/comic_storage8/main/IMAGE/IMAGE_699ba06b8236db9d24f1edeb1e143c06_c979f4919eb191597bcd0feb909c1e54_bd312758f39869c41d25e110f8854f8e.jpg",
    "type" : "image/jpeg",
    "bitrate" : 0,
    "duration" : 0,
    "title" : null,
    "properties" : null,
    "alternate" : [ {
      "href" : "https://i333.ntcdntempv3.com/data/images/19292/907842/066-f0f8fba.jpg?data=net",
      "type" : "image/jpeg",
      "bitrate" : 0,
      "duration" : 0,
      "title" : null,
      "properties" : null,
      "alternate" : null
    } ]
  }, {
    "href" : "https://raw.githubusercontent.com/duyhuynh652018/comic_storage8/main/IMAGE/IMAGE_699ba06b8236db9d24f1edeb1e143c06_c979f4919eb191597bcd0feb909c1e54_5588028b14394f357b093a4c171d5d86.jpg",
    "type" : "image/jpeg",
    "bitrate" : 0,
    "duration" : 0,
    "title" : null,
    "properties" : null,
    "alternate" : [ {
      "href" : "https://i333.ntcdntempv3.com/data/images/19292/907842/067-90f619f.jpg?data=net",
      "type" : "image/jpeg",
      "bitrate" : 0,
      "duration" : 0,
      "title" : null,
      "properties" : null,
      "alternate" : null
    } ]
  } ],
  "toc" : null,
  "@context" : "https://readium.org/webpub-manifest/context.jsonld"
}